<?xml version='1.0' encoding='utf-8'?>
<TextureAtlas imagePath="BF-Sitting.png"><SubTexture name="BF-Sitting Idle0000" x="0" y="0" width="771" height="655" frameX="0" frameY="0" frameWidth="771" frameHeight="655" />
<SubTexture name="BF-Sitting Idle0001" x="771" y="0" width="771" height="655" frameX="0" frameY="0" frameWidth="771" frameHeight="655" />
<SubTexture name="BF-Sitting Idle0002" x="1542" y="0" width="771" height="655" frameX="0" frameY="0" frameWidth="771" frameHeight="655" />
<SubTexture name="BF-Sitting Idle0003" x="2313" y="0" width="771" height="655" frameX="0" frameY="0" frameWidth="771" frameHeight="655" />
<SubTexture name="BF-Sitting Idle0004" x="3084" y="0" width="771" height="655" frameX="0" frameY="0" frameWidth="771" frameHeight="655" />
<SubTexture name="BF-Sitting Idle0005" x="3855" y="0" width="771" height="655" frameX="0" frameY="0" frameWidth="771" frameHeight="655" />
<SubTexture name="BF-Sitting Idle0006" x="4626" y="0" width="771" height="655" frameX="0" frameY="0" frameWidth="771" frameHeight="655" />
<SubTexture name="BF-Sitting Idle0007" x="5397" y="0" width="771" height="655" frameX="0" frameY="0" frameWidth="771" frameHeight="655" />
<SubTexture name="BF-Sitting Idle0008" x="6168" y="0" width="771" height="655" frameX="0" frameY="0" frameWidth="771" frameHeight="655" />
<SubTexture name="BF-Sitting Idle0009" x="0" y="655" width="771" height="655" frameX="0" frameY="0" frameWidth="771" frameHeight="655" />
<SubTexture name="BF-Sitting Idle0010" x="771" y="655" width="771" height="655" frameX="0" frameY="0" frameWidth="771" frameHeight="655" />
<SubTexture name="BF-Sitting Idle0011" x="1542" y="655" width="771" height="655" frameX="0" frameY="0" frameWidth="771" frameHeight="655" />
<SubTexture name="BF-Sitting Idle0012" x="2313" y="655" width="771" height="655" frameX="0" frameY="0" frameWidth="771" frameHeight="655" />
<SubTexture name="BF-Sitting Idle0013" x="3084" y="655" width="771" height="655" frameX="0" frameY="0" frameWidth="771" frameHeight="655" />
<SubTexture name="BF-Sitting Idle0014" x="3855" y="655" width="771" height="655" frameX="0" frameY="0" frameWidth="771" frameHeight="655" />
<SubTexture name="BF-Sitting Idle0015" x="4626" y="655" width="771" height="655" frameX="0" frameY="0" frameWidth="771" frameHeight="655" />
<SubTexture name="BF-Sitting Idle0016" x="5397" y="655" width="771" height="655" frameX="0" frameY="0" frameWidth="771" frameHeight="655" />
<SubTexture name="BF-Sitting Left0000" x="6168" y="655" width="771" height="655" frameX="0" frameY="0" frameWidth="771" frameHeight="655" />
<SubTexture name="BF-Sitting Left0001" x="0" y="1310" width="771" height="655" frameX="0" frameY="0" frameWidth="771" frameHeight="655" />
<SubTexture name="BF-Sitting Left0002" x="771" y="1310" width="771" height="655" frameX="0" frameY="0" frameWidth="771" frameHeight="655" />
<SubTexture name="BF-Sitting Left0003" x="1542" y="1310" width="771" height="655" frameX="0" frameY="0" frameWidth="771" frameHeight="655" />
<SubTexture name="BF-Sitting Left0004" x="2313" y="1310" width="771" height="655" frameX="0" frameY="0" frameWidth="771" frameHeight="655" />
<SubTexture name="BF-Sitting Left0005" x="3084" y="1310" width="771" height="655" frameX="0" frameY="0" frameWidth="771" frameHeight="655" />
<SubTexture name="BF-Sitting Left0006" x="3855" y="1310" width="771" height="655" frameX="0" frameY="0" frameWidth="771" frameHeight="655" />
<SubTexture name="BF-Sitting Left0007" x="4626" y="1310" width="771" height="655" frameX="0" frameY="0" frameWidth="771" frameHeight="655" />
<SubTexture name="BF-Sitting Left0008" x="5397" y="1310" width="771" height="655" frameX="0" frameY="0" frameWidth="771" frameHeight="655" />
<SubTexture name="BF-Sitting Left0009" x="6168" y="1310" width="771" height="655" frameX="0" frameY="0" frameWidth="771" frameHeight="655" />
<SubTexture name="BF-Sitting Left0010" x="0" y="1965" width="771" height="655" frameX="0" frameY="0" frameWidth="771" frameHeight="655" />
<SubTexture name="BF-Sitting Left0011" x="771" y="1965" width="771" height="655" frameX="0" frameY="0" frameWidth="771" frameHeight="655" />
<SubTexture name="BF-Sitting Left0012" x="1542" y="1965" width="771" height="655" frameX="0" frameY="0" frameWidth="771" frameHeight="655" />
<SubTexture name="BF-Sitting Left0013" x="2313" y="1965" width="771" height="655" frameX="0" frameY="0" frameWidth="771" frameHeight="655" />
<SubTexture name="BF-Sitting Left0014" x="3084" y="1965" width="771" height="655" frameX="0" frameY="0" frameWidth="771" frameHeight="655" />
<SubTexture name="BF-Sitting Left0015" x="3855" y="1965" width="771" height="655" frameX="0" frameY="0" frameWidth="771" frameHeight="655" />
<SubTexture name="BF-Sitting Left0016" x="4626" y="1965" width="771" height="655" frameX="0" frameY="0" frameWidth="771" frameHeight="655" />
<SubTexture name="BF-Sitting Right0000" x="5397" y="1965" width="771" height="655" frameX="0" frameY="0" frameWidth="771" frameHeight="655" />
<SubTexture name="BF-Sitting Right0001" x="6168" y="1965" width="771" height="655" frameX="0" frameY="0" frameWidth="771" frameHeight="655" />
<SubTexture name="BF-Sitting Right0002" x="0" y="2620" width="771" height="655" frameX="0" frameY="0" frameWidth="771" frameHeight="655" />
<SubTexture name="BF-Sitting Right0003" x="771" y="2620" width="771" height="655" frameX="0" frameY="0" frameWidth="771" frameHeight="655" />
<SubTexture name="BF-Sitting Right0004" x="1542" y="2620" width="771" height="655" frameX="0" frameY="0" frameWidth="771" frameHeight="655" />
<SubTexture name="BF-Sitting Right0005" x="2313" y="2620" width="771" height="655" frameX="0" frameY="0" frameWidth="771" frameHeight="655" />
<SubTexture name="BF-Sitting Right0006" x="3084" y="2620" width="771" height="655" frameX="0" frameY="0" frameWidth="771" frameHeight="655" />
<SubTexture name="BF-Sitting Right0007" x="3855" y="2620" width="771" height="655" frameX="0" frameY="0" frameWidth="771" frameHeight="655" />
<SubTexture name="BF-Sitting Right0008" x="4626" y="2620" width="771" height="655" frameX="0" frameY="0" frameWidth="771" frameHeight="655" />
<SubTexture name="BF-Sitting Right0009" x="5397" y="2620" width="771" height="655" frameX="0" frameY="0" frameWidth="771" frameHeight="655" />
<SubTexture name="BF-Sitting Right0010" x="6168" y="2620" width="771" height="655" frameX="0" frameY="0" frameWidth="771" frameHeight="655" />
<SubTexture name="BF-Sitting Right0011" x="0" y="3275" width="771" height="655" frameX="0" frameY="0" frameWidth="771" frameHeight="655" />
<SubTexture name="BF-Sitting Right0012" x="771" y="3275" width="771" height="655" frameX="0" frameY="0" frameWidth="771" frameHeight="655" />
<SubTexture name="BF-Sitting Right0013" x="1542" y="3275" width="771" height="655" frameX="0" frameY="0" frameWidth="771" frameHeight="655" />
<SubTexture name="BF-Sitting Right0014" x="2313" y="3275" width="771" height="655" frameX="0" frameY="0" frameWidth="771" frameHeight="655" />
<SubTexture name="BF-Sitting Right0015" x="3084" y="3275" width="771" height="655" frameX="0" frameY="0" frameWidth="771" frameHeight="655" />
<SubTexture name="BF-Sitting Right0016" x="3855" y="3275" width="771" height="655" frameX="0" frameY="0" frameWidth="771" frameHeight="655" />
<SubTexture name="BF-Sitting Up0000" x="4626" y="3275" width="771" height="655" frameX="0" frameY="0" frameWidth="771" frameHeight="655" />
<SubTexture name="BF-Sitting Up0001" x="5397" y="3275" width="771" height="655" frameX="0" frameY="0" frameWidth="771" frameHeight="655" />
<SubTexture name="BF-Sitting Up0002" x="6168" y="3275" width="771" height="655" frameX="0" frameY="0" frameWidth="771" frameHeight="655" />
<SubTexture name="BF-Sitting Up0003" x="0" y="3930" width="771" height="655" frameX="0" frameY="0" frameWidth="771" frameHeight="655" />
<SubTexture name="BF-Sitting Up0004" x="771" y="3930" width="771" height="655" frameX="0" frameY="0" frameWidth="771" frameHeight="655" />
<SubTexture name="BF-Sitting Up0005" x="1542" y="3930" width="771" height="655" frameX="0" frameY="0" frameWidth="771" frameHeight="655" />
<SubTexture name="BF-Sitting Up0006" x="2313" y="3930" width="771" height="655" frameX="0" frameY="0" frameWidth="771" frameHeight="655" />
<SubTexture name="BF-Sitting Up0007" x="3084" y="3930" width="771" height="655" frameX="0" frameY="0" frameWidth="771" frameHeight="655" />
<SubTexture name="BF-Sitting Up0008" x="3855" y="3930" width="771" height="655" frameX="0" frameY="0" frameWidth="771" frameHeight="655" />
<SubTexture name="BF-Sitting Up0009" x="4626" y="3930" width="771" height="655" frameX="0" frameY="0" frameWidth="771" frameHeight="655" />
<SubTexture name="BF-Sitting Up0010" x="5397" y="3930" width="771" height="655" frameX="0" frameY="0" frameWidth="771" frameHeight="655" />
<SubTexture name="BF-Sitting Up0011" x="6168" y="3930" width="771" height="655" frameX="0" frameY="0" frameWidth="771" frameHeight="655" />
<SubTexture name="BF-Sitting Up0012" x="0" y="4585" width="771" height="655" frameX="0" frameY="0" frameWidth="771" frameHeight="655" />
<SubTexture name="BF-Sitting Up0013" x="771" y="4585" width="771" height="655" frameX="0" frameY="0" frameWidth="771" frameHeight="655" />
<SubTexture name="BF-Sitting Up0014" x="1542" y="4585" width="771" height="655" frameX="0" frameY="0" frameWidth="771" frameHeight="655" />
<SubTexture name="BF-Sitting Up0015" x="2313" y="4585" width="771" height="655" frameX="0" frameY="0" frameWidth="771" frameHeight="655" />
<SubTexture name="BF-Sitting Up0016" x="3084" y="4585" width="771" height="655" frameX="0" frameY="0" frameWidth="771" frameHeight="655" />
<SubTexture name="BF-Sitting Down0000" x="3855" y="4585" width="771" height="655" frameX="0" frameY="0" frameWidth="771" frameHeight="655" />
<SubTexture name="BF-Sitting Down0001" x="4626" y="4585" width="771" height="655" frameX="0" frameY="0" frameWidth="771" frameHeight="655" />
<SubTexture name="BF-Sitting Down0002" x="5397" y="4585" width="771" height="655" frameX="0" frameY="0" frameWidth="771" frameHeight="655" />
<SubTexture name="BF-Sitting Down0003" x="6168" y="4585" width="771" height="655" frameX="0" frameY="0" frameWidth="771" frameHeight="655" />
<SubTexture name="BF-Sitting Down0004" x="0" y="5240" width="771" height="655" frameX="0" frameY="0" frameWidth="771" frameHeight="655" />
<SubTexture name="BF-Sitting Down0005" x="771" y="5240" width="771" height="655" frameX="0" frameY="0" frameWidth="771" frameHeight="655" />
<SubTexture name="BF-Sitting Down0006" x="1542" y="5240" width="771" height="655" frameX="0" frameY="0" frameWidth="771" frameHeight="655" />
<SubTexture name="BF-Sitting Down0007" x="2313" y="5240" width="771" height="655" frameX="0" frameY="0" frameWidth="771" frameHeight="655" />
<SubTexture name="BF-Sitting Down0008" x="3084" y="5240" width="771" height="655" frameX="0" frameY="0" frameWidth="771" frameHeight="655" />
<SubTexture name="BF-Sitting Down0009" x="3855" y="5240" width="771" height="655" frameX="0" frameY="0" frameWidth="771" frameHeight="655" />
<SubTexture name="BF-Sitting Down0010" x="4626" y="5240" width="771" height="655" frameX="0" frameY="0" frameWidth="771" frameHeight="655" />
<SubTexture name="BF-Sitting Down0011" x="5397" y="5240" width="771" height="655" frameX="0" frameY="0" frameWidth="771" frameHeight="655" />
<SubTexture name="BF-Sitting Down0012" x="6168" y="5240" width="771" height="655" frameX="0" frameY="0" frameWidth="771" frameHeight="655" />
<SubTexture name="BF-Sitting Down0013" x="0" y="5895" width="771" height="655" frameX="0" frameY="0" frameWidth="771" frameHeight="655" />
<SubTexture name="BF-Sitting Down0014" x="771" y="5895" width="771" height="655" frameX="0" frameY="0" frameWidth="771" frameHeight="655" />
<SubTexture name="BF-Sitting Down0015" x="1542" y="5895" width="771" height="655" frameX="0" frameY="0" frameWidth="771" frameHeight="655" />
<SubTexture name="BF-Sitting Down0016" x="2313" y="5895" width="771" height="655" frameX="0" frameY="0" frameWidth="771" frameHeight="655" />
</TextureAtlas>
